sphinx_cmd/__init__.py
sphinx_cmd/cli.py
sphinx_cmd/config.py
sphinx_cmd/py.typed
sphinx_cmd/commands/__init__.py
sphinx_cmd/commands/mv.py
sphinx_cmd/commands/rm.py
sphinx_cmd-0.5.0.dist-info/licenses/LICENSE
sphinx_cmd-0.5.0.dist-info/METADATA
sphinx_cmd-0.5.0.dist-info/WHEEL
sphinx_cmd-0.5.0.dist-info/entry_points.txt
sphinx_cmd-0.5.0.dist-info/top_level.txt
sphinx_cmd-0.5.0.dist-info/RECORD
