Metadata-Version: 2.4
Name: sphinx-cmd
Version: 0.5.0
Summary: Command-line tools for Sphinx documentation management
Author-email: Jared Dillard <jared.dillard@gmail.com>
Project-URL: Homepage, https://github.com/jdillard/sphinx-cmd
Project-URL: Bug Reports, https://github.com/jdillard/sphinx-cmd/issues
Project-URL: Source, https://github.com/jdillard/sphinx-cmd
Classifier: License :: OSI Approved :: MIT License
Classifier: Operating System :: OS Independent
Classifier: Programming Language :: Python :: 3
Classifier: Programming Language :: Python :: 3.9
Classifier: Programming Language :: Python :: 3.10
Classifier: Programming Language :: Python :: 3.11
Classifier: Programming Language :: Python :: 3.12
Requires-Python: >=3.9
License-File: LICENSE
Requires-Dist: tomli>=2.0.0; python_version < "3.11"
Provides-Extra: dev
Requires-Dist: pytest>=7.0.0; extra == "dev"
Requires-Dist: black; extra == "dev"
Requires-Dist: flake8; extra == "dev"
Requires-Dist: mypy; extra == "dev"
Requires-Dist: isort; extra == "dev"
Requires-Dist: pre-commit; extra == "dev"
Provides-Extra: test
Requires-Dist: pytest>=7.0.0; extra == "test"
Dynamic: license-file
